mathykit/__init__.py
mathykit/core.py
mathykit/version.py
mathykit/models/__init__.py
mathykit/models/meta_opt.py
mathykit/tokenizers/__init__.py
mathykit/tokenizers/meta_tokenizer.py
mathykit-0.1.4.dist-info/licenses/LICENSE
mathykit-0.1.4.dist-info/METADATA
mathykit-0.1.4.dist-info/WHEEL
mathykit-0.1.4.dist-info/top_level.txt
mathykit-0.1.4.dist-info/RECORD
